soylemma/__init__.py
soylemma/hangle.py
soylemma/lemmatizer.py
soylemma/trainer.py
soylemma/utils.py
soylemma/dictionary/default/Adjectives.txt
soylemma/dictionary/default/Eomis.txt
soylemma/dictionary/default/Verbs.txt
soylemma/dictionary/default/rules.txt
soylemma/dictionary/demo/Adjectives.txt
soylemma/dictionary/demo/Eomis.txt
soylemma/dictionary/demo/Verbs.txt
soylemma/dictionary/demo/rules.txt
soylemma-0.2.0.dist-info/METADATA
soylemma-0.2.0.dist-info/WHEEL
soylemma-0.2.0.dist-info/top_level.txt
soylemma-0.2.0.dist-info/RECORD
