Metadata-Version: 2.1
Name: soylemma
Version: 0.2.0
Summary: Trained Korean Lemmatizer
Home-page: https://github.com/lovit/korean_lemmatizer
Author: lovit
Author-email: soy.lovit@gmail.com
License: UNKNOWN
Keywords: korean-nlp,nlp,lemmatizer
Platform: UNKNOWN
Classifier: Programming Language :: Python :: 3.6
Classifier: License :: OSI Approved :: GNU General Public License v3 (GPLv3)
Classifier: Operating System :: OS Independent
